git_cloner/__init__.py
git_cloner/git_cloner.py
django_default-0.0.9.dist-info/LICENSE
django_default-0.0.9.dist-info/METADATA
django_default-0.0.9.dist-info/WHEEL
django_default-0.0.9.dist-info/entry_points.txt
django_default-0.0.9.dist-info/top_level.txt
django_default-0.0.9.dist-info/RECORD
