Metadata-Version: 2.1
Name: django-default
Version: 0.0.9
Summary: A Django project structure generator by @ja_khan_gir
Home-page: https://github.com/JahongirHakimjonov
Author: Jahongir Hakimjonov
Author-email: jahongirhakimjonov@gmail.com
License: MIT
Keywords: django project structure generator
Classifier: Framework :: Django
Classifier: Programming Language :: Python :: 3
Classifier: Operating System :: OS Independent
License-File: LICENSE
Requires-Dist: alive-progress
Requires-Dist: colorama
Requires-Dist: black
Requires-Dist: djangorestframework
Requires-Dist: djangorestframework-simplejwt
Requires-Dist: drf-spectacular
Requires-Dist: drf-spectacular-sidecar
Requires-Dist: Django ==5.0.8
Requires-Dist: django-jazzmin
Requires-Dist: gunicorn
Requires-Dist: pillow
Requires-Dist: psycopg2-binary
Requires-Dist: python-dotenv
Requires-Dist: django-modeltranslation
Requires-Dist: django-ckeditor-5
Requires-Dist: django-cors-headers
Requires-Dist: django-rosetta
Requires-Dist: PyJWT
Requires-Dist: django-unfold
Requires-Dist: django-redis
Requires-Dist: celery
Requires-Dist: flower
